{
  "kind": "singleType",
  "collectionName": "main_menus",
  "info": {
    "singularName": "main-menu",
    "pluralName": "main-menus",
    "displayName": "Main menu",
    "description": ""
  },
  "options": {
    "draftAndPublish": true
  },
  "pluginOptions": {},
  "attributes": {
    "Menu_group": {
      "type": "component",
      "repeatable": true,
      "component": "menus.manu-group"
    },
    "search_field": {
      "type": "string"
    },
    "Social_media_bar": {
      "type": "component",
      "repeatable": true,
      "component": "menus.social-media-bar"
    }
  }
}
