{
  "collectionName": "components_text_boxes_text_and_image_boxes",
  "info": {
    "displayName": "Text_&_image_box"
  },
  "options": {},
  "attributes": {
    "Image": {
      "allowedTypes": [
        "images",
        "files",
        "videos",
        "audios"
      ],
      "type": "media",
      "multiple": false
    },
    "Title": {
      "type": "string"
    },
    "Content": {
      "type": "text"
    },
    "Button": {
      "type": "component",
      "repeatable": true,
      "component": "buttons.simple-button"
    }
  }
}
